agent_skills_sdk/__init__.py
agent_skills_sdk/cli.py
agent_skills_sdk/client.py
agent_skills_sdk/discovery.py
agent_skills_sdk/exceptions.py
agent_skills_sdk/executor.py
agent_skills_sdk/models.py
agent_skills_sdk/parser.py
agent_skills_sdk/adapters/__init__.py
agent_skills_sdk/adapters/agno.py
agent_skills_sdk/adapters/base.py
agent_skills_sdk/adapters/crewai.py
agent_skills_sdk/adapters/langchain.py
agent_skills_sdk-0.1.1.dist-info/METADATA
agent_skills_sdk-0.1.1.dist-info/WHEEL
agent_skills_sdk-0.1.1.dist-info/entry_points.txt
agent_skills_sdk-0.1.1.dist-info/licenses/LICENSE
agent_skills_sdk-0.1.1.dist-info/RECORD
