Metadata-Version: 2.4
Name: agent-skills-sdk
Version: 0.1.1
Summary: Complete SDK for integrating Agent Skills into any Python agent framework
Project-URL: Homepage, https://supreethravi.com
Project-URL: Documentation, https://github.com/supreeth-ravi/agentskills#readme
Project-URL: Repository, https://github.com/supreeth-ravi/agentskills
Project-URL: Bug Tracker, https://github.com/supreeth-ravi/agentskills/issues
Author-email: Supreeth Ravi <connect@supreethravi.com>
License: MIT
License-File: LICENSE
Keywords: agent-skills,agents,agno,ai,crewai,langchain,llm
Classifier: Development Status :: 3 - Alpha
Classifier: Intended Audience :: Developers
Classifier: License :: OSI Approved :: MIT License
Classifier: Programming Language :: Python :: 3
Classifier: Programming Language :: Python :: 3.10
Classifier: Programming Language :: Python :: 3.11
Classifier: Programming Language :: Python :: 3.12
Classifier: Topic :: Scientific/Engineering :: Artificial Intelligence
Classifier: Topic :: Software Development :: Libraries :: Python Modules
Requires-Python: >=3.10
Requires-Dist: aiofiles>=23.0.0
Requires-Dist: httpx>=0.25.0
Requires-Dist: pathspec>=0.11.0
Requires-Dist: pydantic>=2.0.0
Requires-Dist: python-frontmatter>=1.0.0
Requires-Dist: pyyaml>=6.0
Provides-Extra: agno
Requires-Dist: agno>=0.1.0; extra == 'agno'
Provides-Extra: all
Requires-Dist: agno>=0.1.0; extra == 'all'
Requires-Dist: black>=23.0.0; extra == 'all'
Requires-Dist: crewai>=0.1.0; extra == 'all'
Requires-Dist: langchain>=0.1.0; extra == 'all'
Requires-Dist: mypy>=1.5.0; extra == 'all'
Requires-Dist: pytest-asyncio>=0.21.0; extra == 'all'
Requires-Dist: pytest-cov>=4.1.0; extra == 'all'
Requires-Dist: pytest>=7.4.0; extra == 'all'
Requires-Dist: ruff>=0.1.0; extra == 'all'
Provides-Extra: crewai
Requires-Dist: crewai>=0.1.0; extra == 'crewai'
Provides-Extra: dev
Requires-Dist: black>=23.0.0; extra == 'dev'
Requires-Dist: mypy>=1.5.0; extra == 'dev'
Requires-Dist: pytest-asyncio>=0.21.0; extra == 'dev'
Requires-Dist: pytest-cov>=4.1.0; extra == 'dev'
Requires-Dist: pytest>=7.4.0; extra == 'dev'
Requires-Dist: ruff>=0.1.0; extra == 'dev'
Provides-Extra: langchain
Requires-Dist: langchain>=0.1.0; extra == 'langchain'
